MANIFEST.in
README.txt
setup.cfg
setup.py
docs/HISTORY.txt
docs/INSTALL.txt
docs/LICENSE.txt
jalon/.DS_Store
jalon/__init__.py
jalon.theme.egg-info/PKG-INFO
jalon.theme.egg-info/SOURCES.txt
jalon.theme.egg-info/dependency_links.txt
jalon.theme.egg-info/entry_points.txt
jalon.theme.egg-info/namespace_packages.txt
jalon.theme.egg-info/not-zip-safe
jalon.theme.egg-info/paster_plugins.txt
jalon.theme.egg-info/requires.txt
jalon.theme.egg-info/top_level.txt
jalon/theme/__init__.py
jalon/theme/configure.zcml
jalon/theme/profiles.zcml
jalon/theme/setuphandlers.py
jalon/theme/skins.zcml
jalon/theme/tests.py
jalon/theme/version.txt
jalon/theme/browser/.DS_Store
jalon/theme/browser/__init__.py
jalon/theme/browser/configure.zcml
jalon/theme/browser/interfaces.py
jalon/theme/browser/css/app.css
jalon/theme/browser/css/dev.css
jalon/theme/browser/fonts/fontawesome-webfont.eot
jalon/theme/browser/fonts/fontawesome-webfont.svg
jalon/theme/browser/fonts/fontawesome-webfont.ttf
jalon/theme/browser/fonts/fontawesome-webfont.woff
jalon/theme/browser/fonts/fontawesome-webfont.woff2
jalon/theme/browser/fonts/hero-webfont.eot
jalon/theme/browser/fonts/hero-webfont.svg
jalon/theme/browser/fonts/hero-webfont.ttf
jalon/theme/browser/fonts/hero-webfont.woff
jalon/theme/browser/fonts/hero_light-webfont.eot
jalon/theme/browser/fonts/hero_light-webfont.svg
jalon/theme/browser/fonts/hero_light-webfont.ttf
jalon/theme/browser/fonts/hero_light-webfont.woff
jalon/theme/browser/images/favicon.ico
jalon/theme/browser/images/icon-ipad-retina.png
jalon/theme/browser/images/icon-ipad.png
jalon/theme/browser/images/icon-iphone-retina.png
jalon/theme/browser/images/icon-iphone.png
jalon/theme/browser/images/jalon-favicon-128.png
jalon/theme/browser/images/jalon-favicon-16.png
jalon/theme/browser/images/jalon-favicon-24.png
jalon/theme/browser/images/jalon-favicon-256.png
jalon/theme/browser/images/jalon-favicon-32.png
jalon/theme/browser/images/jalon-favicon-48.png
jalon/theme/browser/images/logo-small.svg
jalon/theme/browser/images/logo_uns.svg
jalon/theme/browser/images/logo_uns_uca.svg
jalon/theme/browser/images/mstile.png
jalon/theme/browser/images/stars.svg
jalon/theme/browser/images/tile-large.png
jalon/theme/browser/images/tile-square.png
jalon/theme/browser/images/tile-tiny.png
jalon/theme/browser/images/tile-wide.png
