Metadata-Version: 1.1
Name: jalon.theme
Version: 3.1.5
Summary: An installable theme for Plone 3
Home-page: http://unice.fr
Author: Jerome Navarro, Bordonado Christophe - Université Nice Sophia Antipolis (uns) Service TICE
Author-email: tice@unice.fr
License: CECILL
Platform: UNKNOWN
Classifier: Framework :: Plone
Classifier: Programming Language :: Python
